main.v
module main(clk, rst, data_in, select, data_out);
    parameter DATA_SIZE = 8;
    parameter ROTATION = 0;
    parameter DIRECTION = 0;
    input clk, rst;
    input [DATA_SIZE - 1:0] data_in;
    output reg [DATA_SIZE - 1:0] data_out;
    input [$clog2(DATA_SIZE) - 1:0] select;
    wire [1:0] tmp;
    assign tmp = {ROTATION, DIRECTION};
    always@(posedge clk) begin
        if (!rst) begin
            case (tmp)
                2'b00:
                    data_out <= data_in << select;
                2'b01:
                    data_out <= data_in >> select;
                2'b10:
                    data_out <= {data_in, data_in} << select;
                2'b11:
                    data_out <= {data_in, data_in} >> select;
            endcase
        end
    end
endmodule

test_2.v
module test_2();
    parameter DATA_SIZE = 16;
    parameter ROTATION = 1'b1;
    parameter DIRECTION = 1'b1;
    reg clk, rst;
    reg [DATA_SIZE - 1:0] data_in;
    reg [$clog2(DATA_SIZE) - 1:0] select;
    wire [DATA_SIZE - 1:0] data_out;
    main #(DATA_SIZE, ROTATION, DIRECTION) _main(.clk(clk), .rst(rst), .data_in(data_in), .select(select), .data_out(data_out));
    initial begin
        $dumpfile("dump2.vcd");
        $dumpvars(0, test_2);
        #20
        $finish;
    end
    initial begin
        #2
        rst = 1;
        #2
        rst = 0;
        data_in = 16'b0001_1001_0000_0001;
        select = 4'b0011;
        #2
        data_in = 16'b1001_0111_1000_1011;
        select = 4'b0010;
        #2
        data_in = 16'b0001_0001_1000_1001;
        select = 4'b0100;
        #2
        data_in = 16'b1101_1001_0001_1101;
        select = 4'b0100;
    end
    initial clk = 0;
    always #1 clk = !clk;
endmodule

dump2.vcd
$date
	Sat Oct 29 04:03:13 2022
$end
$version
	Icarus Verilog
$end
$timescale
	1s
$end
$scope module test_2 $end
$var wire 16 ! data_out [15:0] $end
$var reg 1 " clk $end
$var reg 16 # data_in [15:0] $end
$var reg 1 $ rst $end
$var reg 4 % select [3:0] $end
$scope module _main $end
$var wire 1 & clk $end
$var wire 16 ' data_in [15:0] $end
$var wire 1 ( rst $end
$var wire 4 ) select [3:0] $end
$var wire 2 * tmp [1:0] $end
$var reg 16 + data_out [15:0] $end
$upscope $end
$upscope $end
$enddefinitions $end
#0
$dumpvars
bx +
b11 *
bx )
x(
bx '
0&
bx %
x$
bx #
0"
bx !
$end
#1
1"
1&
#2
0"
0&
1$
1(
#3
1"
1&
#4
0"
0&
b11 %
b11 )
b1100100000001 #
b1100100000001 '
0$
0(
#5
b10001100100000 +
b10001100100000 !
1"
1&
#6
0"
0&
b10 %
b10 )
b1001011110001011 #
b1001011110001011 '
#7
b1110010111100010 +
b1110010111100010 !
1"
1&
#8
0"
0&
b100 %
b100 )
b1000110001001 #
b1000110001001 '
#9
b1001000100011000 +
b1001000100011000 !
1"
1&
#10
0"
0&
b1101100100011101 #
b1101100100011101 '
#11
b1101110110010001 +
b1101110110010001 !
1"
1&
