main.v
module main(clk, rst, data_in, select, data_out);
    parameter DATA_SIZE = 8;
    parameter ROTATION = 0;
    parameter DIRECTION = 0;
    input clk, rst;
    input [DATA_SIZE - 1:0] data_in;
    output reg [DATA_SIZE - 1:0] data_out;
    input [$clog2(DATA_SIZE) - 1:0] select;
    wire [1:0] tmp;
    assign tmp = {ROTATION, DIRECTION};
    always@(posedge clk) begin
        if (!rst) begin
            case (tmp)
                2'b00:
                    data_out <= data_in << select;
                2'b01:
                    data_out <= data_in >> select;
                2'b10:
                    data_out <= {data_in, data_in} << select;
                2'b11:
                    data_out <= {data_in, data_in} >> select;
            endcase
        end
    end
endmodule

test_1.v
module test_1();
    parameter DATA_SIZE = 8;
    parameter ROTATION = 1'b0;
    parameter DIRECTION = 1'b1;
    reg clk, rst;
    reg [DATA_SIZE - 1:0] data_in;
    reg [$clog2(DATA_SIZE) - 1:0] select;
    wire [DATA_SIZE - 1:0] data_out;
    main #(DATA_SIZE, ROTATION, DIRECTION) _main(.clk(clk), .rst(rst), .data_in(data_in), .select(select), .data_out(data_out));
    initial begin
        $dumpfile("dump1.vcd");
        $dumpvars(0, test_1);
        #15
        $finish;
    end
    initial begin
        #2
        rst = 1;
        #2
        rst = 0;
        data_in = 8'b0001_1001;
        select = 3'b001;
        #2
        data_in = 8'b1001_0111;
        select = 3'b010;
        #2
        data_in = 8'b1011_0001;
        select = 3'b011;
        #2
        data_in = 8'b1000_0101;
        select = 3'b100;
        #2
        data_in = 8'b1001_0000;
        select = 3'b101;
    end
    initial clk = 0;
    always #1 clk = !clk;
endmodule

dump1.vcd
$date
	Sat Oct 29 03:53:33 2022
$end
$version
	Icarus Verilog
$end
$timescale
	1s
$end
$scope module test_1 $end
$var wire 8 ! data_out [7:0] $end
$var reg 1 " clk $end
$var reg 8 # data_in [7:0] $end
$var reg 1 $ rst $end
$var reg 3 % select [2:0] $end
$scope module _main $end
$var wire 1 & clk $end
$var wire 8 ' data_in [7:0] $end
$var wire 1 ( rst $end
$var wire 3 ) select [2:0] $end
$var wire 2 * tmp [1:0] $end
$var reg 8 + data_out [7:0] $end
$upscope $end
$upscope $end
$enddefinitions $end
#0
$dumpvars
bx +
b1 *
bx )
x(
bx '
0&
bx %
x$
bx #
0"
bx !
$end
#1
1"
1&
#2
0"
0&
1$
1(
#3
1"
1&
#4
0"
0&
b1 %
b1 )
b11001 #
b11001 '
0$
0(
#5
b1100 +
b1100 !
1"
1&
#6
0"
0&
b10 %
b10 )
b10010111 #
b10010111 '
#7
b100101 +
b100101 !
1"
1&
#8
0"
0&
b11 %
b11 )
b10110001 #
b10110001 '
#9
b10110 +
b10110 !
1"
1&
#10
0"
0&
b100 %
b100 )
b10000101 #
b10000101 '
#11
b1000 +
b1000 !
1"
1&
#12
0"
0&
b101 %
b101 )
b10010000 #
b10010000 '
#13
b100 +
b100 !
1"
1&
